rest_framework-stubs/__init__.pyi
rest_framework-stubs/apps.pyi
rest_framework-stubs/authentication.pyi
rest_framework-stubs/authtoken/__init__.pyi
rest_framework-stubs/authtoken/admin.pyi
rest_framework-stubs/authtoken/apps.pyi
rest_framework-stubs/authtoken/management/__init__.pyi
rest_framework-stubs/authtoken/management/commands/__init__.pyi
rest_framework-stubs/authtoken/management/commands/drf_create_token.pyi
rest_framework-stubs/authtoken/models.pyi
rest_framework-stubs/authtoken/serializers.pyi
rest_framework-stubs/authtoken/views.pyi
rest_framework-stubs/checks.pyi
rest_framework-stubs/compat.pyi
rest_framework-stubs/decorators.pyi
rest_framework-stubs/documentation.pyi
rest_framework-stubs/exceptions.pyi
rest_framework-stubs/fields.pyi
rest_framework-stubs/filters.pyi
rest_framework-stubs/generics.pyi
rest_framework-stubs/management/__init__.pyi
rest_framework-stubs/management/commands/__init__.pyi
rest_framework-stubs/management/commands/generateschema.pyi
rest_framework-stubs/metadata.pyi
rest_framework-stubs/mixins.pyi
rest_framework-stubs/negotiation.pyi
rest_framework-stubs/pagination.pyi
rest_framework-stubs/parsers.pyi
rest_framework-stubs/permissions.pyi
rest_framework-stubs/relations.pyi
rest_framework-stubs/renderers.pyi
rest_framework-stubs/request.pyi
rest_framework-stubs/response.pyi
rest_framework-stubs/reverse.pyi
rest_framework-stubs/routers.pyi
rest_framework-stubs/schemas/__init__.pyi
rest_framework-stubs/schemas/coreapi.pyi
rest_framework-stubs/schemas/generators.pyi
rest_framework-stubs/schemas/inspectors.pyi
rest_framework-stubs/schemas/openapi.pyi
rest_framework-stubs/schemas/utils.pyi
rest_framework-stubs/schemas/views.pyi
rest_framework-stubs/serializers.pyi
rest_framework-stubs/settings.pyi
rest_framework-stubs/status.pyi
rest_framework-stubs/templatetags/__init__.pyi
rest_framework-stubs/templatetags/rest_framework.pyi
rest_framework-stubs/test.pyi
rest_framework-stubs/throttling.pyi
rest_framework-stubs/urlpatterns.pyi
djangorestframework_stubs-3.16.4.dist-info/licenses/LICENSE.txt
djangorestframework_stubs-3.16.4.dist-info/WHEEL
djangorestframework_stubs-3.16.4.dist-info/METADATA
djangorestframework_stubs-3.16.4.dist-info/RECORD
