Metadata-Version: 2.4
Name: djangorestframework-stubs
Version: 3.16.4
Summary: PEP-484 stubs for django-rest-framework
Author: Maksim Kurnikov
Author-email: Maksim Kurnikov <maxim.kurnikov@gmail.com>
License-Expression: MIT
License-File: LICENSE.txt
Classifier: License :: OSI Approved :: MIT License
Classifier: Operating System :: OS Independent
Classifier: Programming Language :: Python :: 3.10
Classifier: Programming Language :: Python :: 3.11
Classifier: Programming Language :: Python :: 3.12
Classifier: Programming Language :: Python :: 3.13
Classifier: Typing :: Typed
Classifier: Framework :: Django
Requires-Dist: django-stubs>=5.2.5
Requires-Dist: typing-extensions>=4.0
Requires-Dist: requests>=2.0
Requires-Dist: types-requests
Requires-Dist: types-pyyaml
Requires-Dist: mypy>=1.13,<1.19 ; extra == 'compatible-mypy'
Requires-Dist: django-stubs[compatible-mypy] ; extra == 'compatible-mypy'
Requires-Dist: coreapi>=2.0.0 ; extra == 'coreapi'
Requires-Dist: types-markdown>=0.1.5 ; extra == 'markdown'
Maintainer: Marti Raudsepp, Nikita Sobolev
Maintainer-email: Marti Raudsepp <marti@juffo.org>, Nikita Sobolev <mail@sobolevn.me>
Requires-Python: >=3.10
Project-URL: Funding, https://github.com/sponsors/typeddjango
Project-URL: Homepage, https://github.com/typeddjango/djangorestframework-stubs
Project-URL: Release notes, https://github.com/typeddjango/djangorestframework-stubs/releases
Provides-Extra: compatible-mypy
Provides-Extra: coreapi
Provides-Extra: markdown
